README.txt
setup.py
agent/__init__.py
agent/exclussive_context.py
agent/logging_context.py
agent/pidfile.py
ptallada_agent.egg-info/PKG-INFO
ptallada_agent.egg-info/SOURCES.txt
ptallada_agent.egg-info/dependency_links.txt
ptallada_agent.egg-info/requires.txt
ptallada_agent.egg-info/top_level.txt
ptallada_agent.egg-info/zip-safe