Metadata-Version: 1.1
Name: ptallada-agent
Version: 1.0.0
Summary: A wrapper around python-daemon to change pidfile handling.
Home-page: http://packages.python.org/python-agent
Author: Pau Tallada Crespí
Author-email: pau.tallada@gmail.com
License: AGPLv3+
Keywords: daemon agent singleton pid background
Platform: UNKNOWN
Classifier: Development Status :: 5 - Production/Stable
Classifier: Intended Audience :: Developers
Classifier: License :: OSI Approved :: GNU Affero General Public License v3 or later (AGPLv3+)
Classifier: Programming Language :: Python
Classifier: Operating System :: OS Independent
Classifier: Topic :: Software Development :: Libraries :: Python Modules
Classifier: Topic :: Utilities
